mmllm_face_refinement/__init__.py
mmllm_face_refinement/detector.py
mmllm_face_refinement/face_detector.py
mmllm_face_refinement/llm_analyzer.py
mmllm_face_refinement-0.1.12.dist-info/licenses/LICENSE
mmllm_face_refinement-0.1.12.dist-info/METADATA
mmllm_face_refinement-0.1.12.dist-info/WHEEL
mmllm_face_refinement-0.1.12.dist-info/entry_points.txt
mmllm_face_refinement-0.1.12.dist-info/top_level.txt
mmllm_face_refinement-0.1.12.dist-info/RECORD
