Metadata-Version: 2.4
Name: mmllm-face-refinement
Version: 0.1.12
Summary: Face detection and LLM-based face refinement using YOLO and multimodal LLMs (Gemini, LLaVA).
Author-email: Your Name <your@email.com>
License: MIT
Project-URL: Homepage, https://github.com/yourusername/mmllm-face-refinement
Project-URL: Documentation, https://github.com/yourusername/mmllm-face-refinement#readme
Project-URL: Repository, https://github.com/yourusername/mmllm-face-refinement.git
Project-URL: Bug Tracker, https://github.com/yourusername/mmllm-face-refinement/issues
Keywords: face-detection,llm,yolo,gemini,llava,computer-vision
Classifier: Development Status :: 4 - Beta
Classifier: Intended Audience :: Developers
Classifier: Programming Language :: Python :: 3
Classifier: Programming Language :: Python :: 3.8
Classifier: Programming Language :: Python :: 3.9
Classifier: Programming Language :: Python :: 3.10
Classifier: Topic :: Scientific/Engineering :: Artificial Intelligence
Classifier: Topic :: Scientific/Engineering :: Image Recognition
Requires-Python: >=3.8
License-File: LICENSE
Requires-Dist: numpy
Requires-Dist: opencv-python
Requires-Dist: torch
Requires-Dist: torchvision
Requires-Dist: pillow
Requires-Dist: pyyaml
Requires-Dist: requests
Requires-Dist: matplotlib
Requires-Dist: supervision
Requires-Dist: ultralytics
Requires-Dist: transformers
Requires-Dist: python-dotenv
Requires-Dist: google-generativeai
Requires-Dist: accelerate
Requires-Dist: bitsandbytes
Requires-Dist: sentencepiece
Requires-Dist: tqdm
Requires-Dist: onnx
Requires-Dist: protobuf
Requires-Dist: tensorboard
Requires-Dist: safetensors
Requires-Dist: jsonschema
Dynamic: license-file
